secret/SCRATCH.py
secret/__init__.py
tests/__init__.py
tests/__main__.py
tkstyle/__init__.py
tkstyle/__main__.py
tkstyle/error/__init__.py
tkstyle/hooking/__init__.py
tkstyle/hooking/ante_build_hook.py
tkstyle/hooking/ante_release_hook.py
tkstyle/hooking/post_build_hook.py
tkstyle/hooking/post_release_hook.py
tkstyle/pyrustic_data/hooking.json
tkstyle/pyrustic_data/hubstore.json
tkstyle/pyrustic_data/release_info.json
tkstyle/pyrustic_data/backstage/config/build.json
tkstyle/pyrustic_data/backstage/config/init.json
tkstyle/pyrustic_data/backstage/config/release.json
tkstyle/pyrustic_data/backstage/data/build_report.json
tkstyle/pyrustic_data/backstage/data/github_release_form.json
tkstyle/pyrustic_data/backstage/hooking/build.json
tkstyle/pyrustic_data/backstage/hooking/init.json
tkstyle/pyrustic_data/backstage/hooking/release.json
tkstyle/pyrustic_data/backstage/report/build_report.json
tkstyle/pyrustic_data/backstage/report/release_report.json
tkstyle/pyrustic_data/hubstore/img.json
tkstyle/pyrustic_data/hubstore/promotion.json
tkstyle-0.0.6.dist-info/LICENSE
tkstyle-0.0.6.dist-info/METADATA
tkstyle-0.0.6.dist-info/WHEEL
tkstyle-0.0.6.dist-info/entry_points.txt
tkstyle-0.0.6.dist-info/top_level.txt
tkstyle-0.0.6.dist-info/RECORD
