Metadata-Version: 2.1
Name: tkstyle
Version: 0.0.6
Summary: Create styles and themes for your Python desktop applications
Home-page: https://github.com/pyrustic/tkstyle
Author: Pyrustic Evangelist
Author-email: rusticalex@yahoo.com
Maintainer: Pyrustic Evangelist
Maintainer-email: rusticalex@yahoo.com
License: MIT
Keywords: theme,style,theme-builder,app,gui,library,frontend,productivity,pyrustic,theme,desktop-application,lightweight
Platform: UNKNOWN
Classifier: Programming Language :: Python :: 3
Classifier: License :: OSI Approved :: MIT License
Classifier: Operating System :: OS Independent
Requires-Python: >=3.5
License-File: LICENSE
